emailer_simple_tool/__init__.py
emailer_simple_tool/cli.py
emailer_simple_tool/core/__init__.py
emailer_simple_tool/core/campaign_manager.py
emailer_simple_tool/core/email_sender.py
emailer_simple_tool/core/picture_generator.py
emailer_simple_tool/gui/__init__.py
emailer_simple_tool/gui/main_window.py
emailer_simple_tool/gui/main_window.py.backup
emailer_simple_tool/gui/translation_manager.py
emailer_simple_tool/gui/help/en/about.md
emailer_simple_tool/gui/help/en/campaign_setup.md
emailer_simple_tool/gui/help/en/email_sending.md
emailer_simple_tool/gui/help/en/faq.md
emailer_simple_tool/gui/help/en/picture_generator.md
emailer_simple_tool/gui/help/en/quick_start.md
emailer_simple_tool/gui/help/en/smtp_config.md
emailer_simple_tool/gui/help/en/troubleshooting.md
emailer_simple_tool/gui/help/fr/about.md
emailer_simple_tool/gui/help/fr/campaign_setup.md
emailer_simple_tool/gui/help/fr/email_sending.md
emailer_simple_tool/gui/help/fr/faq.md
emailer_simple_tool/gui/help/fr/picture_generator.md
emailer_simple_tool/gui/help/fr/quick_start.md
emailer_simple_tool/gui/help/fr/smtp_config.md
emailer_simple_tool/gui/help/fr/troubleshooting.md
emailer_simple_tool/gui/tabs/__init__.py
emailer_simple_tool/gui/tabs/campaign_tab.py
emailer_simple_tool/gui/tabs/help_tab.py
emailer_simple_tool/gui/tabs/picture_tab.py
emailer_simple_tool/gui/tabs/send_tab.py
emailer_simple_tool/gui/tabs/smtp_tab.py
emailer_simple_tool/gui/translations/emailer_simple_tool_fr.qm
emailer_simple_tool/gui/translations/emailer_simple_tool_fr.ts
emailer_simple_tool/gui/translations/emailer_simple_tool_fr_backup.qm
emailer_simple_tool/gui/translations/emailer_simple_tool_fr_backup.ts
emailer_simple_tool/gui/translations/emailer_simple_tool_fr_new.qm
emailer_simple_tool/gui/translations/emailer_simple_tool_fr_new.ts
emailer_simple_tool/gui/translations/emailer_simple_tool_fr_restored.qm
emailer_simple_tool/gui/translations/emailer_simple_tool_fr_restored.ts
emailer_simple_tool-11.0.0.dist-info/licenses/LICENSE
emailer_simple_tool-11.0.0.dist-info/METADATA
emailer_simple_tool-11.0.0.dist-info/WHEEL
emailer_simple_tool-11.0.0.dist-info/entry_points.txt
emailer_simple_tool-11.0.0.dist-info/top_level.txt
emailer_simple_tool-11.0.0.dist-info/RECORD
