Metadata-Version: 2.4
Name: emailer-simple-tool
Version: 11.0.0
Summary: A personalized email campaign management tool
Home-page: https://github.com/delhomaws/emailer-simple-tool
Author: INAO Team
Author-email: INAO Team <contact@inao.org>
Maintainer-email: INAO Team <contact@inao.org>
License: MIT
Project-URL: Homepage, https://github.com/delhomaws/emailer-simple-tool
Project-URL: Documentation, https://github.com/delhomaws/emailer-simple-tool#documentation
Project-URL: Repository, https://github.com/delhomaws/emailer-simple-tool
Project-URL: Bug Tracker, https://github.com/delhomaws/emailer-simple-tool/issues
Project-URL: Changelog, https://github.com/delhomaws/emailer-simple-tool/blob/main/CHANGELOG.md
Keywords: email,campaign,personalization,bulk-email,marketing
Classifier: Development Status :: 4 - Beta
Classifier: Intended Audience :: End Users/Desktop
Classifier: License :: OSI Approved :: MIT License
Classifier: Operating System :: OS Independent
Classifier: Programming Language :: Python :: 3
Classifier: Programming Language :: Python :: 3.8
Classifier: Programming Language :: Python :: 3.9
Classifier: Programming Language :: Python :: 3.10
Classifier: Programming Language :: Python :: 3.11
Classifier: Programming Language :: Python :: 3.12
Classifier: Topic :: Communications :: Email
Classifier: Topic :: Office/Business
Classifier: Environment :: Console
Classifier: Natural Language :: English
Classifier: Natural Language :: French
Requires-Python: >=3.8
License-File: LICENSE
Requires-Dist: cryptography>=3.4.8
Requires-Dist: click>=8.0.0
Requires-Dist: Pillow>=8.0.0
Requires-Dist: python-docx>=0.8.11
Provides-Extra: gui
Requires-Dist: PySide6>=6.0.0; extra == "gui"
Provides-Extra: dev
Requires-Dist: pytest>=6.0.0; extra == "dev"
Requires-Dist: pytest-cov>=2.12.0; extra == "dev"
Requires-Dist: black>=21.0.0; extra == "dev"
Requires-Dist: flake8>=3.9.0; extra == "dev"
Requires-Dist: mypy>=0.910; extra == "dev"
Requires-Dist: build>=0.8.0; extra == "dev"
Requires-Dist: twine>=4.0.0; extra == "dev"
Provides-Extra: all
Requires-Dist: PySide6>=6.0.0; extra == "all"
Requires-Dist: pytest>=6.0.0; extra == "all"
Requires-Dist: pytest-cov>=2.12.0; extra == "all"
Requires-Dist: black>=21.0.0; extra == "all"
Requires-Dist: flake8>=3.9.0; extra == "all"
Requires-Dist: mypy>=0.910; extra == "all"
Requires-Dist: build>=0.8.0; extra == "all"
Requires-Dist: twine>=4.0.0; extra == "all"
Dynamic: author
Dynamic: home-page
Dynamic: license-file
Dynamic: requires-python
